django_ratelimit/__init__.py
django_ratelimit/apps.py
django_ratelimit/checks.py
django_ratelimit/core.py
django_ratelimit/decorators.py
django_ratelimit/exceptions.py
django_ratelimit/middleware.py
django_ratelimit/models.py
django_ratelimit/tests.py
djangorestframework_ratelimit-1.0.0.dist-info/LICENSE
djangorestframework_ratelimit-1.0.0.dist-info/METADATA
djangorestframework_ratelimit-1.0.0.dist-info/WHEEL
djangorestframework_ratelimit-1.0.0.dist-info/top_level.txt
djangorestframework_ratelimit-1.0.0.dist-info/RECORD
