Metadata-Version: 2.1
Name: djangorestframework-ratelimit
Version: 1.0.0
Summary: Cache-based rate-limiting for Django and Django REST Framework
Author-email: James Socol <me@jamessocol.com>, Ronan Boiteau <ronan@boiteau.eu>
Maintainer-email: Ronan Boiteau <ronan@boiteau.eu>
License: Copyright (c) 2022, James Socol
Project-URL: Documentation, https://github.com/ronanboiteau/djangorestframework-ratelimit/blob/main/README.md
Project-URL: Repository, https://github.com/ronanboiteau/djangorestframework-ratelimit.git
Project-URL: Issues, https://github.com/ronanboiteau/djangorestframework-ratelimit/issues
Project-URL: Changelog, https://github.com/ronanboiteau/djangorestframework-ratelimit/blob/main/CHANGELOG.md
Keywords: django,rest,framework,ratelimit,rate,limit
Classifier: Development Status :: 5 - Production/Stable
Classifier: Environment :: Web Environment
Classifier: Intended Audience :: Developers
Classifier: License :: OSI Approved :: Apache Software License
Classifier: Operating System :: OS Independent
Classifier: Programming Language :: Python
Classifier: Programming Language :: Python :: 3
Classifier: Programming Language :: Python :: 3.7
Classifier: Programming Language :: Python :: 3.8
Classifier: Programming Language :: Python :: 3.9
Classifier: Programming Language :: Python :: 3.10
Classifier: Programming Language :: Python :: 3.11
Classifier: Framework :: Django
Classifier: Framework :: Django :: 3.2
Classifier: Framework :: Django :: 4.0
Classifier: Framework :: Django :: 4.1
Classifier: Framework :: Django :: 4.2
Classifier: Topic :: Software Development :: Libraries :: Python Modules
Requires-Python: >=3.7
License-File: LICENSE
Requires-Dist: django >=3.2
